cove/__init__.py
cove/app.py
cove/request.py
cove_python-0.1.0.dist-info/DESCRIPTION.rst
cove_python-0.1.0.dist-info/METADATA
cove_python-0.1.0.dist-info/RECORD
cove_python-0.1.0.dist-info/WHEEL
cove_python-0.1.0.dist-info/metadata.json
cove_python-0.1.0.dist-info/top_level.txt
