Metadata-Version: 2.0
Name: cove-python
Version: 0.1.0
Summary: https://cove.sh Python library
Home-page: https://github.com/cove-dev/cove-python
Author: Cove
Author-email: dev@cove.sh
License: MIT
Download-URL: https://github.com/cove-dev/cove-python/archive/0.1.tar.gz
Keywords: cove functions http
Platform: UNKNOWN
Classifier: Intended Audience :: Developers
Classifier: License :: OSI Approved :: MIT License
Classifier: Development Status :: 5 - Production/Stable
Classifier: Programming Language :: Python :: 3 :: Only
Classifier: Programming Language :: Python :: 3.5
Classifier: Programming Language :: Python :: 3.6
Classifier: Programming Language :: Python :: 3.7
Classifier: Topic :: Internet :: WWW/HTTP
Classifier: Topic :: Software Development
Requires-Python: ~=3.5
Requires-Dist: werkzeug (>=0.12)
